tap_rickandmorty/__init__.py
tap_rickandmorty/client.py
tap_rickandmorty/streams.py
tap_rickandmorty/tap.py
tap_rickandmorty/tests/__init__.py
tap_rickandmorty/tests/test_core.py
tap_rickandmorty-0.0.1.dist-info/entry_points.txt
tap_rickandmorty-0.0.1.dist-info/WHEEL
tap_rickandmorty-0.0.1.dist-info/METADATA
tap_rickandmorty-0.0.1.dist-info/RECORD
