Metadata-Version: 2.1
Name: tap-rickandmorty
Version: 0.0.1
Summary: `tap-rickandmorty` is a Singer tap for RickAndMorty, built with the Meltano SDK for Singer Taps.
License: Apache 2.0
Keywords: ELT,RickAndMorty
Author: nyawnga
Requires-Python: >=3.7.1,<3.11
Classifier: License :: Other/Proprietary License
Classifier: Programming Language :: Python :: 3
Classifier: Programming Language :: Python :: 3.8
Classifier: Programming Language :: Python :: 3.9
Requires-Dist: requests (>=2.25.1,<3.0.0)
Requires-Dist: singer-sdk (>=0.4.4,<0.5.0)
